{
  "Resumo": "Sou especialista em Análise de Sistemas com mais de 15 anos de experiência em desenvolvimento de software, análise de sistemas, integração de plataformas e resolução de problemas.  Minha expertise inclui habiliades de observabilidade e sustentação, AWS, APIs REST/SOAP, Salesforce e Desenvolvimento de Sistemas (Java, Node.js, Python, Go e .NET).  Tenho orgulho de liderar equipes e entregar soluções tecnológicas robustas, priorizando eficiência operacional, inovação e resultados mensuráveis.  Certificado em SRE, com especialização em Data Science, Business Agility e AWS, combino conhecimentos técnicos e visão estratégica para gerenciar projetos complexos.  Além disso, me destaco pela criação de ambientes colaborativos e pelo impacto positivo em equipes e organizações.  Adoro desafios onde posso aliar expertise técnica, visão de negócios e práticas ágeis para alcançar resultados transformadores. ",
  "Competências_Chave": [
    "Arquitetura de sistemas e integração de APIs ",
    "Liderança técnica e gestão ágil ",
    "Data Science e Visualização de Dados ",
    "Certificações em AWS Cloud e SRE Essentials "
  ],
  "Formação_Academica": [
    {
      "Instituição": "Universidade Presbiteriana Mackenzie",
      "Curso": "Pós-graduação em Ciência de Dados – Data Analytics / Big Data",
      "Período": "Fevereiro de 2019 – Julho de 2021",
      "Diploma_Digital_Codigo": "EED4D2846DDD86592422CC674AB449"
    },
    {
      "Instituição": "Universidade Presbiteriana Mackenzie",
      "Curso": "Bacharelado em Sistemas de Informação, com ênfase em Logística e Cadeia de Suprimentos",
      "Ano": "2001 – 2005"
    },
    {
      "Instituição": "Colégio Guarani",
      "Curso": "Curso Técnico em Processamento de Dados",
      "Período": "1997 – 1999"
    }
  ],
  "Certificados": [
    {
      "Nome": "Kony Certified Developer",
      "Instituição": "Kony, Inc.",
      "Data_Emissao": "abril de 2016",
      "Codigo_Credencial": "KC10061571463"
    },
    {
      "Nome": "AWS Profissional Technical",
      "Instituição": "Amazon Web Services (AWS) ",
      "Data_Emissao": "abril de 2017 "
    },
    {
      "Nome": "Workshop Salesforce para Desenvolvedores",
      "Instituição": "Salesforce",
      "Data_Emissao": "dezembro de 2017",
      "Verificação": "https://cursos.alura.com.br/certificate/17c88e93-13d1-4ac2-826c-7254c53a93a0"
    },
    {
      "Nome": "Formação Salesforce Trailhead",
      "Instituição": "Salesforce",
      "Ano": "2018",
      "Verificação": "https://www.salesforce.com/trailblazer/issei"
    },
    {
      "Nome": "Formação e Capacitação Alura",
      "Instituição": "Alura",
      "Período": "13/03/2018 a 10/12/2024",
      "Verificação": "https://cursos.alura.com.br/user/mauricio-issei/fullCertificate/8c92662d32a5ec2020d3bd9066f610e0"
    },
    {
      "Nome": "Design Think",
      "Instituição": "FIAP",
      "Data_Emissao": "março de 2021",
      "Verificação": "https://on.fiap.com.br/local/nanocourses/gerar_certificado.php?chave=5aeee13691392217120b14b94ffb905b&action=view"
    },
    {
      "Nome": "Inteligência Artificial",
      "Instituição": "FIAP",
      "Data_Emissao": "março de 2021",
      "Codigo_Credencial": "d49e69fc55f98e0ce7abeeabba01fe8f ",
      "Verificação": "https://on.fiap.com.br/local/nanocourses/gerar_certificado.php?chave=d49e69fc55f98e0ce7abeeabba01fe8f&action=view "
    },
    {
      "Nome": "UX",
      "Instituição": "FIAP",
      "Data_Emissao": "março de 2021",
      "Verificação": "https://on.fiap.com.br/local/nanocourses/gerar_certificado.php?chave=78eb0d83a5db0aadce891455e7d54dfb&action=view "
    },
    {
      "Nome": "SRE Essentials",
      "Instituição": "Itcerts",
      "Data_Emissao": "março de 2021",
      "Codigo_Credencial": "30760715",
      "Verificação": "https://www.credential.net/c07a4ff4-8839-43e3-8d23-2edef6446458 "
    },
    {
      "Nome": "AWS Certified Cloud Practitioner",
      "Instituição": "Amazon Web Services (AWS)",
      "Data_Emissao": "janeiro de 2022",
      "Verificação": "https://www.credly.com/badges/439e9244-9403-459d-b0ed-02aa51652951?source=linked_in_profile "
    },
    {
      "Nome": "Arquitetura de Soluções",
      "Instituição": "Itaú Unibanco",
      "Data_Emissao": "30 de abril de 2022",
      "Codigo_Credencial": "259032928 ",
      "Verificação": "http://badges.com.br/share/113a264018cdb4367fce684877af45d1.php?a=2148 "
    },
    {
      "Nome": "Practitioner – D&A Foundation",
      "Instituição": "Itaú Unibanco",
      "Data_Emissao": "27 de novembro de 2023",
      "Verificação": "http://badges.com.br/share/96939e18d6e0d41488339e14dc93d614.php?a=3694 "
    },
    {
      "Nome": "Practitioner – D&A Foundation",
      "Instituição": "Itaú Unibanco",
      "Data_Emissao": "29 de maio de 2024",
      "Verificação": "https://www.credly.com/badges/1f596ad2-9834-45b7-99f0-298eddd56cb7 "
    },
    {
      "Nome": "Practitioner – Generative AI",
      "Instituição": "Itaú Unibanco",
      "Data_Emissao": "27 de junho de 2024",
      "Verificação": "https://www.credly.com/badges/231cd871-ab40-4c65-8834-e9ca77792f56 "
    },
    {
      "Nome": "Practitioner – Leadership D&A",
      "Instituição": "Itaú Unibanco",
      "Data_Emissao": "31 de julho de 2024 ",
      "Verificação": "https://www.credly.com/badges/a8dad682-bc42-4978-b085-ae720cbd8667 "
    },
    {
      "Nome": "Arquitetura de Soluções",
      "Instituição": "Itaú Unibanco",
      "Data_Emissao": "26 de setembro de 2024",
      "Verificação": "https://www.credly.com/badges/92fc3afc-6e11-4433-9a44-8dc5f6215dd0 "
    },
    {
      "Nome": "Troubleshooting com Datadog",
      "Instituição": "Appoena",
      "Data_Emissao": "outubro de 2024",
      "Verificação": "https://badges.com.br/share/2e2541209f996bea07bc41521d86e4a3.php?a=7527 "
    },
    {
      "Nome": "Datadog Power User",
      "Instituição": "Appoena",
      "Data_Emissao": "fevereiro de 2025",
      "Verificação": "https://badges.com.br/share/465eef0a1c14fc6a0383f3a805d294d0.php?a=7683 "
    },
    {
      "Nome": "AI for Leaders",
      "Instituição": "StartSe University",
      "Data_Emissao": "abril de 2025",
      "Codigo_Credencial": "678fc9c0f8158077f9db505c ",
      "Verificação": "https://lms.startse.com/certificado/v2/678fc9c0f8158077f9db505c?studentId=5e337f0a99763dac88d37e79 "
    }
  ],
  "Experiencia": [
    {
      "Empresa": "Rede",
      "Cargo": "Tech Lead",
      "Período": "fev de 2018 – o momento (7 anos e 6 meses) ",
      "Local": "São Paulo, São Paulo, Brasil · Híbrida ",
      "Descrição": "Líder Técnico responsável por soluções na plataforma Salesforce, com arquiteturas de integração on-premise e AWS.  Atua na definição e desenvolvimento de melhores práticas, fortalecendo a base de conhecimento corporativa, com foco nas necessidades dos clientes. ",
      "Competências": [
        "Salesforce Administration ",
        "SRE "
      ]
    },
    {
      "Empresa": "Serasa Experian",
      "Cargo": "Analista de Desenvolvimento",
      "Período": "dez de 2017 – jan de 2018 (2 meses) ",
      "Local": "São Paulo, Brasil ",
      "Descrição": "Atuação na equipe de Digital Strategy, contribuindo para o desenvolvimento da API corporativa de OAuth 2 e cadastro unificado.  Participação no projeto Serasa Empreendedor.  Projeto ágil com Scrum, arquitetura API First, utilizando Java (Spring), Swagger, testes automatizados com JUnit e Cucumber, integração contínua com Jenkins, versionamento com Git, gerenciamento de APIs com Apigee e infraestrutura em AWS. ",
      "Competências": [
        "Amazon Web Services ",
        "Experiência do usuário (UX) "
      ]
    },
    {
      "Empresa": "Indra",
      "Cargo": "Senior Java / Mobile Systems Analyst",
      "Período": "fev de 2012 – dez de 2017 (5 anos e 11 meses) ",
      "Local": "São Paulo, Brasil ",
      "Descrição": "Liderança da equipe de desenvolvimento de sistemas para clientes da área de seguros.  Responsável por levantamento e análise de requisitos, definição de arquitetura de soluções, controle de qualidade, relacionamento com o cliente e sustentação. ",
      "Principais_Projetos": [
        "Líder técnico de time de inovação, com propostas e soluções Mobile e AWS (arquiteturas serverless, microserviços, Android nativo, Ionic, DevOps) ",
        "Sistema de seguros com Java, JBoss Seam, Spring, RichFaces, Oracle PL/SQL ",
        "Sustentação e evolução de sistemas de apoio operacional "
      ],
      "Competências": [
        "Liderança de equipe ",
        "Amazon Web Services "
      ]
    },
    {
      "Empresa": "Sysgen",
      "Cargo": "Analista Programador Java",
      "Período": "ago de 2003 – jan de 2012 (8 anos e 6 meses) ",
      "Descrição": "Desenvolvimento de aplicações web e de console em Java (J2EE e J2SE), utilizando framework ASPER e arquitetura MVC.  Aplicações baseadas em modelagem UML, com geração de código via MDA (Model-Driven Architecture) pela ferramenta Celero, focadas nas regras de negócio. ",
      "Competência": "Liderança de equipe "
    },
    {
      "Empresa": "Telefônica",
      "Cargo": "Analista de Desenvolvimento Java",
      "Período": "abr de 2005 – set de 2008 (3 anos e 6 meses) ",
      "Local": "São Paulo, Brasil ",
      "Descrição": "Desenvolvimento de sistema de gestão de almoxarifado de peças e sistema de aprovisionamento de rede. ",
      "Competência": "Liderança de equipe "
    }
  ],
  "Projetos": [
    {
      "Nome": "Serasa Empreendedor",
      "Período": "dez de 2017 – jan de 2018",
      "Empresa": "Serasa Experian",
      "Descrição": "Participação no desenvolvimento do portal Serasa Empreendedor, com foco em APIs corporativas, OAuth 2 e cadastro unificado. "
    },
    {
      "Nome": "App Restaurante America",
      "Período": "fev de 2017 – dez de 2017",
      "Empresa": "Indra",
      "Descrição": "Desenvolvimento de aplicativo móvel para o Restaurante América, disponível para Android e iOS. "
    },
    {
      "Nome": "Equipe de Inovação",
      "Período": "mar de 2016 – dez de 2017",
      "Empresa": "Indra",
      "Descrição": "Apoio ao time comercial na elaboração de propostas técnicas, desenho de soluções, arquitetura e desenvolvimento de provas de conceito.  Atuação em projetos de transformação digital em múltiplas verticais. "
    },
    {
      "Nome": "BB Mapfre Seguros",
      "Período": "fev de 2012 – mar de 2016",
      "Empresa": "Indra",
      "Descrição": "Líder técnico no desenvolvimento do sistema de emissão de propostas do seguro Empresarial Simplificado.  Posteriormente assumiu a sustentação deste sistema e de outros sistemas relacionados à captação de sinistros. "
    },
    {
      "Nome": "LMS – Contém 1g",
      "Descrição": "Sistema de Gestão de Cursos a Distância – Tácito em Explícito ",
      "Período": "dez de 2011 – fev de 2012",
      "Empresa": "Sysgen",
      "Tecnologias": "Adobe Flex, BlazeDS, Java 1.5, JBoss, Tomcat, EJB, DB2, PostgreSQL, SCORM. "
    },
    {
      "Nome": "BamCentric – Sistema de Gerenciamento de Eventos (BAM)",
      "Período": "jul de 2010 – dez de 2011",
      "Empresa": "Sysgen",
      "Descrição": "Desenvolvimento de sistema para gerenciamento de eventos corporativos. "
    },
    {
      "Nome": "ERP para Metalúrgica Nhozinho",
      "Período": "out de 2008 – jul de 2010",
      "Empresa": "Sysgen",
      "Descrição": "Atuação como analista de sistemas e programador no desenvolvimento de ERP customizado. ",
      "Tecnologias": "HTML, JavaScript, Java 1.4, EJB, JBoss, JFreeChart, JasperReports, Sockets, XML, PostgreSQL. "
    },
    {
      "Nome": "Fênix – Sistema de Aprovisionamento de Rede",
      "Período": "set de 2006 – set de 2008",
      "Empresa": "Telefônica SP",
      "Descrição": "Desenvolvimento e liderança da equipe técnica no sistema de aprovisionamento de rede. ",
      "Tecnologias": "Java 1.4, EJB, JBoss, JFreeChart, JasperReports, Oracle. "
    },
    {
      "Nome": "Sistema de Atualização de Taxas Monetárias – GE Money",
      "Período": "jun de 2006 – set de 2006",
      "Empresa": "Sysgen",
      "Descrição": "Sistema automatizado de captura de terminal 3270 e atualização de taxas monetárias. ",
      "Tecnologias": "Java 1.4, EJB, JBoss, JFreeChart, JasperReports, MS SQL Server. "
    },
    {
      "Nome": "SGRS – Sistema de Controle de Sobressalentes",
      "Período": "abr de 2005 – jul de 2006",
      "Empresa": "Telefônica SP",
      "Descrição": "Sistema de controle de peças sobressalentes para operações internas. "
    },
    {
      "Nome": "Sistema de Empréstimo Consignado – BicBanco",
      "Período": "jul de 2004 – mar de 2005",
      "Empresa": "Sysgen",
      "Descrição": "Desenvolvimento de sistema de crédito consignado para instituição financeira. "
    },
    {
      "Nome": "Sistema de Controle de Acesso e Perfil – Intermédica Saúde",
      "Período": "jan de 2004 – jul de 2004",
      "Empresa": "Sysgen",
      "Descrição": "Sistema para gerenciamento de perfis e controle de acesso dos usuários internos. "
    }
  ],
  "Recomendacoes_Recebidas": [
    {
      "Autor": "Mylena Mancilha",
      "Cargo": "Produtos Digitais | Meios de Pagamento | Growth | Salesforce | Gestão Ágil ",
      "Data_Trabalho": "18 de setembro de 2024 – trabalhou com Maurício na mesma equipe ",
      "Recomendacao": "Tive o prazer de trabalhar ao lado do Issei ao longo deste ano, e não poderia deixar de destacar suas qualidades excepcionais.  Sua capacidade técnica é impressionante, sempre acompanhada de uma disposição incansável para colaborar e compartilhar seu conhecimento.  Ele é extremamente dedicado, garantindo a entrega de soluções de alta qualidade e um legado duradouro.  Além disso, Issei se destaca pelo excelente relacionamento interpessoal, sempre inspirando as pessoas ao seu redor.  Juntos, conseguimos criar um ambiente de trabalho positivo, aberto ao aprendizado, onde a comunicação e a colaboração fluem naturalmente. "
    },
    {
      "Autor": "Saulo Oliveira",
      "Cargo": "Desenvolvedor .NET ",
      "Data_Trabalho": "6 de julho de 2023 – respondia a Maurício ",
      "Recomendacao": "É com grande prazer que escrevo esta recomendação para o Maurício Issei.  Tive a oportunidade de trabalhar com o Maurício em alguns projetos grandes e desafiadores e fiquei profundamente impressionado com sua habilidade de inspirar e liderar a equipe.  Maurício é um profissional excepcional, cujo comprometimento e dedicação são evidentes em todas as tarefas que realiza.  Sua paixão pelo trabalho é contagiante, e ele é capaz de motivar seus colegas a alcançarem seu melhor desempenho.  Uma das características mais marcantes de Maurício é sua liderança e seu trabalho em equipe.  Ele possui uma visão clara e estratégica, capaz de guiar o grupo em direção aos objetivos estabelecidos.  Sua capacidade de tomar decisões rápidas e eficazes, mesmo em situações de pressão, é notável.  É importante ressaltar que a expertise profissional de Maurício é impressionante.  Ele possui um conhecimento aprofundado em sua área de atuação, sempre atualizado com as últimas tendências e melhores práticas.  Eu recomendo Maurício Issei sem hesitação. Se você tiver a oportunidade de trabalhar com ele ou tê-lo em sua equipe, estará diante de um líder inspirador e um profissional exemplar. "
    },
    {
      "Autor": "Vinicius Custodio",
      "Cargo": "Software Engineer at Shape Digital ",
      "Data_Trabalho": "2 de agosto de 2021 – trabalhou com Maurício na mesma equipe ",
      "Recomendacao": "O Maurício é extremamente profissional e objetivo para resolução de problemas.  Tem uma visão holística em relação ao negócio e arquitetura de sistemas.  No tempo em que trabalhamos juntos, tive oportunidade de aprender e evoluir profissionalmente. "
    },
    {
      "Autor": "Paulo Soderi Noronha",
      "Cargo": "Project Manager at Indra USA ",
      "Data_Trabalho": "24 de abril de 2017 – trabalhou com Maurício na mesma equipe ",
      "Recomendacao": "I worked with Mauricio in different projects and technologies, in every situation Mauricio succeeded to high level of quality.  Mauricio is a very strong team player, always able to help someone else.  He is a fast learner and has a strong technical knowledge. Mauricio also appreciates and delivers a very clean code.  I recommend Mauricio and desire to work with him soon. "
    },
    {
      "Autor": "Laercio Lamarca",
      "Cargo": "Executive Manager | Driving Revenue Growth Strategies ",
      "Data_Trabalho": "21 de abril de 2017 – supervisionava Maurício diretamente ",
      "Recomendacao": "Maurício é um profissional com alto padrão de performance.  Reconhecido por seus pares, clientes e colaboradores.  Toma riscos de forma madura e equilibrada, atingindo sempre os objetivos. "
    },
    {
      "Autor": "Rogerio Cruz",
      "Cargo": "Project Manager | PMO | IT Risk Specialist ",
      "Data_Trabalho": "7 de abril de 2015 – supervisionava Maurício diretamente ",
      "Recomendacao": "Tive a honra de ter o Mauricio na minha equipe, profissional altamente competente, confiável, parceiro, adapta-se facilmente em qualquer tipo de projeto.  Seus trabalhos são entregues sempre dentro do prazo, com baixo índice de retrabalho e rejeições.  Como arquiteto de soluções, esteve presente em diversos projetos, propondo e desenvolvendo soluções de alta complexidade.  Tornou-se referência para o cliente e a própria Indra.  Espero poder trabalharmos juntos novamente. "
    },
    {
      "Autor": "Fatima dos S. M. Maximo",
      "Cargo": "PMP, SPC-SAFe, ITIL, PSM, Six Sigma, COBIT5 – Secretaria da Fazenda SP ",
      "Data_Trabalho": "8 de novembro de 2012 – era cliente de Maurício ",
      "Recomendacao": "Mauricio focuses on results, has knowledge of the tools used, and follows the agreed schedule for the projects. "
    },
    {
      "Autor": "Kleper de Souza Ramos Filho",
      "Cargo": "Technical Director - LATAM at Keyrus ",
      "Data_Trabalho": "4 de agosto de 2012 – era cliente de Maurício ",
      "Recomendacao": "Mauricio is the kind of person in which you can count on for the most difficult tasks, always helpful and ready to give the right solution on time. "
    },
    {
      "Autor": "Luiz Fracalanzza",
      "Cargo": "Business Director | Defense & Security ",
      "Data_Trabalho": "18 de junho de 2010 – era cliente de Maurício ",
      "Recomendacao": "Mauricio is a great SW developer, attentive to details of the deal, participative and committed to their activities and tasks.  He showed maturity and talent facing the challenges of diverse situations and projects. "
    },
    {
      "Autor": "Felipe Caparelli",
      "Cargo": "Especialista Java e Engenheiro de Software ",
      "Data_Trabalho": "10 de junho de 2010 – trabalhou com Maurício em empresas diferentes ",
      "Recomendacao": "Grande profissional com qualidades técnicas e gerenciais em nível avançado.  Muito bom tê-lo novamente como parceiro aqui na KF. "
    },
    {
      "Autor": "Aldo Bina",
      "Cargo": "Engenheiro de Telecomunicações ",
      "Data_Trabalho": "7 de junho de 2010 – trabalhou com Maurício na mesma equipe ",
      "Recomendacao": "Mauricio é muito inteligente, compenetrado e dedicado em seu trabalho, preocupando-se sempre com a qualidade do trabalho realizado, sem descuidar dos prazos acordados. "
    },
    {
      "Autor": "William Braga Dal Mas, PMP",
      "Cargo": "Consultor | Gerente de Projetos | Agilista ",
      "Data_Trabalho": "7 de junho de 2010 – supervisionava Maurício diretamente ",
      "Recomendacao": "Com elevada produtividade e análise apurada, Maurício soube tirar proveito em todas as reuniões do projeto e sugeriu boas alternativas quando problemas ocorreram. "
    },
    {
      "Autor": "Celso Pina",
      "Cargo": "Head de Delivery na GFT Technologies ",
      "Data_Trabalho": "7 de junho de 2010 – trabalhou com Maurício em equipes diferentes ",
      "Recomendacao": "O Mauricio tem excelente conhecimento técnico e alto grau de comprometimento com as atividades a ele atribuídas e responsáveis. "
    },
    {
      "Autor": "Ingo Passos",
      "Cargo": "Desenvolvedor Java | Analista de Sistemas ",
      "Data_Trabalho": "15 de abril de 2010 – supervisionava Maurício diretamente ",
      "Recomendacao": "Mauricio is the kind of professional who cares to share knowledge with their colleagues, has an excellent logical reasoning and is always looking for new tools to help your work. "
    }
  ],
  "Cursos_Alura": {
    "Desenvolvimento_de_Software_e_Programação": [
      "SOLID com Java: Orientação a Objetos com Java (8h) ",
      "Docker: Criando containers sem dor de cabeça (10h) ",
      "Java OO: entendendo a Orientação a Objetos (8h) ",
      "HTTP: Entendendo a web por baixo dos panos (14h) ",
      "JavaScript: de padrões a uma abordagem funcional (10h) ",
      "Maratona de Programação (12h) ",
      "Machine Learning com Java: Sistema de recomendações (8h) ",
      "Spring Boot API REST: construa uma API (8h) ",
      "Spring Boot API Rest: Segurança, Cache e Monitoramento (12h) ",
      "MLOps: Machine Learning e APIs (10h) ",
      "Segurança Web: vulnerabilidades e OWASP (12h) ",
      "Git e Github (6h) ",
      "Vue3: explorando o framework (8h) ",
      "Machine Learning: classificação com SKLearn (8h) ",
      "Internet das Coisas: Python (6h) "
    ],
    "Data_Science_e_Análise_de_Dados": [
      "Data Science: análise e visualização de dados (6h) ",
      "Data Science: testes estatísticos com Python (6h) ",
      "Data Visualization parte 1: introdução ao design de gráficos (15h) ",
      "Data Visualization parte 2: Escolhendo o melhor gráfico (6h) ",
      "R: análise de dados (8h) ",
      "Estatística I: Entenda seus dados com R (8h) ",
      "Estatística II: Aprofundando em hipóteses e correlações (8h) ",
      "Machine Learning: validação de modelos (8h) ",
      "Análise e visualização de dados com R (8h) ",
      "Data Mesh: abordagem distribuída para dados (8h) "
    ],
    "Gestão_e_Metodologias_Ágeis": [
      "Lean Startup: primeiros passos da sua Startup enxuta (5h) ",
      "Agile avançado: crie modelos e descubra o Nexus (10h) ",
      "Agile na prática: técnicas aplicadas para Gestão Ágil (8h) ",
      "Agile Coach, Práticas Ágeis, Organização de Equipes Ágeis, Gestão Ágil, A Empresa Ágil, Agilidade (36h) ",
      "Gestão de produtos digitais: Produto vs Projeto, Validação, Aceleração (18h) ",
      "Gestão Ágil: explorando conceitos da agilidade (8h) ",
      "Métricas Ágeis (6h) ",
      "Kanban parte 1 (6h) ",
      "Equipes ágeis: organizando os papéis (8h) "
    ],
    "Liderança_e_Habilidades_Interpessoais": [
      "Foco: trazendo mais resultados para o dia a dia (10h) ",
      "Comunicação: como se expressar bem e ser compreendido (8h) ",
      "Introdução a Pitch: o primeiro passo para apresentações de impacto (8h) ",
      "Liderança parte 1: Seja líder no novo mercado (8h) ",
      "Liderança parte 2: seja o líder que o mercado procura (12h) ",
      "Estresse parte 1: buscando qualidade de vida (5h) ",
      "Estresse parte 2: equilibre seu estilo de vida (8h) ",
      "Feedback: a arte de orientar e ser orientado com sentido (5h) ",
      "Pontos fortes parte 1 e 2 (8h) ",
      "Profissão Tech Lead (8h) ",
      "Tech Lead: práticas e rotinas de gestão (10h) ",
      "Tech Lead: guiando para alta performance (8h) ",
      "Relacionamento interpessoal parte 2 (6h) "
    ],
    "UX_e_Design": [
      "Design Thinking parte 1/2/3 (27h) ",
      "UX Strategy: divergindo e afunilando ideias (12h) ",
      "Design Thinking: viabilizando soluções (8h) "
    ],
    "Infraestrutura_e_Cloud": [
      "Amazon Code Deploy (12h) ",
      "Linux I (4h)",
      "Linux II (8h)",
      "AWS Certified Cloud Practitioner: Domain 1 a 4 (18h)",
      "Amazon S3 (12h)",
      "Deploy no Amazon EC2 (10h)"
    ],
    "Outros": [
      "Gerenciamento de inovação organizacional parte 1 (10h)",
      "LGPD: conhecendo e entendendo seus impactos (159)",
      "Landing Page: construindo sua campanha (8h)"
    ]
  }
}